{
    "last_updated": "2026-04-16 17:01",
    "stocks": [
        {
            "symbol": "CMG",
            "name": "Chipotle Mexican Grill, Inc.",
            "price": 35.085,
            "score": 58.4,
            "metrics": {
                "PEG": 5,
                "ROE": "47%",
                "PE": 25.8
            },
            "tag": "Growth Gem",
            "reason": "Market Cap: $46.4B | PEG: 5"
        },
        {
            "symbol": "TSCO",
            "name": "Tractor Supply Company",
            "price": 44.8601,
            "score": 53.0,
            "metrics": {
                "PEG": 5,
                "ROE": "45%",
                "PE": 18.7
            },
            "tag": "Growth Gem",
            "reason": "Market Cap: $23.6B | PEG: 5"
        },
        {
            "symbol": "NWSA",
            "name": "News Corporation",
            "price": 25.775,
            "score": 40,
            "metrics": {
                "PEG": 5,
                "ROE": "6%",
                "PE": 20.6
            },
            "tag": "Growth Gem",
            "reason": "Market Cap: $14.9B | PEG: 5"
        },
        {
            "symbol": "CSGP",
            "name": "CoStar Group, Inc.",
            "price": 39.93,
            "score": 40,
            "metrics": {
                "PEG": 5,
                "ROE": "0%",
                "PE": 22.4
            },
            "tag": "Growth Gem",
            "reason": "Market Cap: $16.9B | PEG: 5"
        },
        {
            "symbol": "GIS",
            "name": "General Mills, Inc.",
            "price": 35.19,
            "score": 40,
            "metrics": {
                "PEG": 5,
                "ROE": "24%",
                "PE": 10.7
            },
            "tag": "Hidden Value",
            "reason": "Market Cap: $18.8B | PEG: 5"
        },
        {
            "symbol": "CMCSA",
            "name": "Comcast Corporation",
            "price": 29.065,
            "score": 40,
            "metrics": {
                "PEG": 5,
                "ROE": "21%",
                "PE": 7.5
            },
            "tag": "Hidden Value",
            "reason": "Market Cap: $105.9B | PEG: 5"
        },
        {
            "symbol": "TAP",
            "name": "Molson Coors Beverage Company",
            "price": 44.49,
            "score": 40,
            "metrics": {
                "PEG": 5,
                "ROE": "-18%",
                "PE": 8.9
            },
            "tag": "Hidden Value",
            "reason": "Market Cap: $8.4B | PEG: 5"
        },
        {
            "symbol": "HST",
            "name": "Host Hotels & Resorts, Inc.",
            "price": 20.595,
            "score": 40,
            "metrics": {
                "PEG": 5,
                "ROE": "11%",
                "PE": 21.4
            },
            "tag": "Growth Gem",
            "reason": "Market Cap: $14.3B | PEG: 5"
        },
        {
            "symbol": "PCG",
            "name": "Pacific Gas & Electric Co.",
            "price": 17.245,
            "score": 40,
            "metrics": {
                "PEG": 5,
                "ROE": "8%",
                "PE": 9.6
            },
            "tag": "Hidden Value",
            "reason": "Market Cap: $38.0B | PEG: 5"
        },
        {
            "symbol": "KIM",
            "name": "Kimco Realty Corporation (HC)",
            "price": 23.495,
            "score": 40,
            "metrics": {
                "PEG": 5,
                "ROE": "6%",
                "PE": 27.5
            },
            "tag": "Growth Gem",
            "reason": "Market Cap: $15.8B | PEG: 5"
        },
        {
            "symbol": "NI",
            "name": "NiSource Inc",
            "price": 47.15,
            "score": 40,
            "metrics": {
                "PEG": 5,
                "ROE": "9%",
                "PE": 21.2
            },
            "tag": "Growth Gem",
            "reason": "Market Cap: $22.6B | PEG: 5"
        },
        {
            "symbol": "HPE",
            "name": "Hewlett Packard Enterprise Comp",
            "price": 25.485,
            "score": 40,
            "metrics": {
                "PEG": 5,
                "ROE": "0%",
                "PE": 9.4
            },
            "tag": "Hidden Value",
            "reason": "Market Cap: $33.9B | PEG: 5"
        },
        {
            "symbol": "VTRS",
            "name": "Viatris Inc.",
            "price": 13.765,
            "score": 40,
            "metrics": {
                "PEG": 5,
                "ROE": "-21%",
                "PE": 5.2
            },
            "tag": "Hidden Value",
            "reason": "Market Cap: $16.0B | PEG: 5"
        },
        {
            "symbol": "FIS",
            "name": "Fidelity National Information S",
            "price": 48.785,
            "score": 40,
            "metrics": {
                "PEG": 5,
                "ROE": "3%",
                "PE": 7.1
            },
            "tag": "Hidden Value",
            "reason": "Market Cap: $25.3B | PEG: 5"
        },
        {
            "symbol": "PFE",
            "name": "Pfizer, Inc.",
            "price": 27.2227,
            "score": 40,
            "metrics": {
                "PEG": 5,
                "ROE": "9%",
                "PE": 9.7
            },
            "tag": "Hidden Value",
            "reason": "Market Cap: $154.9B | PEG: 5"
        },
        {
            "symbol": "RF",
            "name": "Regions Financial Corporation",
            "price": 27.82,
            "score": 40,
            "metrics": {
                "PEG": 5,
                "ROE": "12%",
                "PE": 9.8
            },
            "tag": "Hidden Value",
            "reason": "Market Cap: $24.0B | PEG: 5"
        },
        {
            "symbol": "LUV",
            "name": "Southwest Airlines Company",
            "price": 40.92,
            "score": 40,
            "metrics": {
                "PEG": 5,
                "ROE": "5%",
                "PE": 9.0
            },
            "tag": "Hidden Value",
            "reason": "Market Cap: $20.1B | PEG: 5"
        },
        {
            "symbol": "SMCI",
            "name": "Super Micro Computer, Inc.",
            "price": 28.055,
            "score": 40,
            "metrics": {
                "PEG": 5,
                "ROE": "13%",
                "PE": 9.3
            },
            "tag": "Hidden Value",
            "reason": "Market Cap: $16.8B | PEG: 5"
        },
        {
            "symbol": "PPL",
            "name": "PPL Corporation",
            "price": 38.98,
            "score": 40,
            "metrics": {
                "PEG": 5,
                "ROE": "8%",
                "PE": 18.4
            },
            "tag": "Growth Gem",
            "reason": "Market Cap: $29.3B | PEG: 5"
        },
        {
            "symbol": "NCLH",
            "name": "Norwegian Cruise Line Holdings ",
            "price": 20.305,
            "score": 40,
            "metrics": {
                "PEG": 5,
                "ROE": "23%",
                "PE": 8.1
            },
            "tag": "Hidden Value",
            "reason": "Market Cap: $9.2B | PEG: 5"
        }
    ]
}