{
    "last_updated": "2026-04-16 07:18",
    "stocks": [
        {
            "symbol": "CMG",
            "name": "Chipotle Mexican Grill, Inc.",
            "price": 35.25,
            "score": 58.4,
            "metrics": {
                "PEG": 5,
                "ROE": "47%",
                "PE": 25.9
            },
            "tag": "Growth Gem",
            "reason": "Market Cap: $46.6B | PEG: 5"
        },
        {
            "symbol": "TSCO",
            "name": "Tractor Supply Company",
            "price": 44.75,
            "score": 53.0,
            "metrics": {
                "PEG": 5,
                "ROE": "45%",
                "PE": 18.7
            },
            "tag": "Growth Gem",
            "reason": "Market Cap: $23.6B | PEG: 5"
        },
        {
            "symbol": "MGM",
            "name": "MGM Resorts International",
            "price": 38.36,
            "score": 40,
            "metrics": {
                "PEG": 5,
                "ROE": "15%",
                "PE": 16.4
            },
            "tag": "Hidden Value",
            "reason": "Market Cap: $10.5B | PEG: 5"
        },
        {
            "symbol": "NI",
            "name": "NiSource Inc",
            "price": 47.37,
            "score": 40,
            "metrics": {
                "PEG": 5,
                "ROE": "9%",
                "PE": 21.3
            },
            "tag": "Growth Gem",
            "reason": "Market Cap: $22.7B | PEG: 5"
        },
        {
            "symbol": "CPB",
            "name": "The Campbell's Company",
            "price": 20.49,
            "score": 40,
            "metrics": {
                "PEG": 5,
                "ROE": "14%",
                "PE": 9.1
            },
            "tag": "Hidden Value",
            "reason": "Market Cap: $6.1B | PEG: 5"
        },
        {
            "symbol": "PFE",
            "name": "Pfizer, Inc.",
            "price": 27.19,
            "score": 40,
            "metrics": {
                "PEG": 5,
                "ROE": "9%",
                "PE": 9.7
            },
            "tag": "Hidden Value",
            "reason": "Market Cap: $154.7B | PEG: 5"
        },
        {
            "symbol": "CAG",
            "name": "ConAgra Brands, Inc.",
            "price": 14.09,
            "score": 40,
            "metrics": {
                "PEG": 5,
                "ROE": "-1%",
                "PE": 8.3
            },
            "tag": "Hidden Value",
            "reason": "Market Cap: $6.7B | PEG: 5"
        },
        {
            "symbol": "FITB",
            "name": "Fifth Third Bancorp",
            "price": 49.84,
            "score": 40,
            "metrics": {
                "PEG": 5,
                "ROE": "12%",
                "PE": 10.2
            },
            "tag": "Hidden Value",
            "reason": "Market Cap: $45.1B | PEG: 5"
        },
        {
            "symbol": "NWSA",
            "name": "News Corporation",
            "price": 25.33,
            "score": 40,
            "metrics": {
                "PEG": 5,
                "ROE": "6%",
                "PE": 20.4
            },
            "tag": "Growth Gem",
            "reason": "Market Cap: $14.6B | PEG: 5"
        },
        {
            "symbol": "ARE",
            "name": "Alexandria Real Estate Equities",
            "price": 47.61,
            "score": 40,
            "metrics": {
                "PEG": 5,
                "ROE": "-6%",
                "PE": -595.1
            },
            "tag": "Hidden Value",
            "reason": "Market Cap: $8.3B | PEG: 5"
        },
        {
            "symbol": "KHC",
            "name": "The Kraft Heinz Company",
            "price": 22.01,
            "score": 40,
            "metrics": {
                "PEG": 5,
                "ROE": "-13%",
                "PE": 10.3
            },
            "tag": "Hidden Value",
            "reason": "Market Cap: $26.1B | PEG: 5"
        },
        {
            "symbol": "KMI",
            "name": "Kinder Morgan, Inc.",
            "price": 31.7,
            "score": 40,
            "metrics": {
                "PEG": 5,
                "ROE": "10%",
                "PE": 21.6
            },
            "tag": "Growth Gem",
            "reason": "Market Cap: $70.5B | PEG: 5"
        },
        {
            "symbol": "NKE",
            "name": "Nike, Inc.",
            "price": 45.44,
            "score": 40,
            "metrics": {
                "PEG": 5,
                "ROE": "16%",
                "PE": 24.2
            },
            "tag": "Growth Gem",
            "reason": "Market Cap: $67.3B | PEG: 5"
        },
        {
            "symbol": "BAX",
            "name": "Baxter International Inc.",
            "price": 17.6,
            "score": 40,
            "metrics": {
                "PEG": 5,
                "ROE": "-14%",
                "PE": 8.7
            },
            "tag": "Hidden Value",
            "reason": "Market Cap: $9.1B | PEG: 5"
        },
        {
            "symbol": "FIS",
            "name": "Fidelity National Information S",
            "price": 48.32,
            "score": 40,
            "metrics": {
                "PEG": 5,
                "ROE": "3%",
                "PE": 7.0
            },
            "tag": "Hidden Value",
            "reason": "Market Cap: $25.0B | PEG: 5"
        },
        {
            "symbol": "CTRA",
            "name": "Coterra Energy Inc.",
            "price": 31.6,
            "score": 40,
            "metrics": {
                "PEG": 5,
                "ROE": "12%",
                "PE": 10.4
            },
            "tag": "Hidden Value",
            "reason": "Market Cap: $24.0B | PEG: 5"
        },
        {
            "symbol": "TTD",
            "name": "The Trade Desk, Inc.",
            "price": 22.38,
            "score": 40,
            "metrics": {
                "PEG": 5,
                "ROE": "16%",
                "PE": 9.4
            },
            "tag": "Hidden Value",
            "reason": "Market Cap: $10.7B | PEG: 5"
        },
        {
            "symbol": "PSKY",
            "name": "Paramount Skydance Corporation",
            "price": 11.67,
            "score": 40,
            "metrics": {
                "PEG": 5,
                "ROE": "-1%",
                "PE": 12.5
            },
            "tag": "Hidden Value",
            "reason": "Market Cap: $13.0B | PEG: 5"
        },
        {
            "symbol": "EXC",
            "name": "Exelon Corporation",
            "price": 47.88,
            "score": 40,
            "metrics": {
                "PEG": 5,
                "ROE": "10%",
                "PE": 15.7
            },
            "tag": "Hidden Value",
            "reason": "Market Cap: $49.0B | PEG: 5"
        },
        {
            "symbol": "MOS",
            "name": "Mosaic Company (The)",
            "price": 23.73,
            "score": 40,
            "metrics": {
                "PEG": 5,
                "ROE": "5%",
                "PE": 9.7
            },
            "tag": "Hidden Value",
            "reason": "Market Cap: $7.5B | PEG: 5"
        }
    ]
}